replay_wizard/__init__.py
replay_wizard/__main__.py
replay_wizard/package.py
replay_wizard/storage.py
replay_wizard/capturing/__init__.py
replay_wizard/capturing/capture.py
replay_wizard/capturing/errors.py
replay_wizard/capturing/keyboard.py
replay_wizard/capturing/mouse.py
replay_wizard/cli/__init__.py
replay_wizard/cli/capture.py
replay_wizard/cli/combine.py
replay_wizard/cli/parser.py
replay_wizard/cli/replay.py
replay_wizard/cli/utils.py
replay_wizard/models/__init__.py
replay_wizard/models/action.py
replay_wizard/models/keyboard.py
replay_wizard/models/mouse.py
replay_wizard/models/time_sequence.py
replay_wizard/replay/__init__.py
replay_wizard/replay/keyboard.py
replay_wizard/replay/mouse.py
replay_wizard/replay/replay.py
replay_wizard-2.3.1.dist-info/LICENSE
replay_wizard-2.3.1.dist-info/METADATA
replay_wizard-2.3.1.dist-info/WHEEL
replay_wizard-2.3.1.dist-info/entry_points.txt
replay_wizard-2.3.1.dist-info/top_level.txt
replay_wizard-2.3.1.dist-info/RECORD
