Metadata-Version: 2.1
Name: replay-wizard
Version: 2.3.1
Summary: ReplayWizard is a powerful automation tool designed to streamline your workflow by capturing and replaying your interactions with your computer
Home-page: https://github.com/quillcraftsman/replay-wizard
Author: quillcraftsman
Author-email: quill@craftsman.lol
License: MIT
Project-URL: Documentation, https://replaywizard.craftsman.lol/
Project-URL: Source, https://github.com/quillcraftsman/replay-wizard
Project-URL: Tracker, https://github.com/quillcraftsman/replay-wizard/issues
Project-URL: Release notes, https://github.com/quillcraftsman/replay-wizard/releases
Project-URL: Changelog, https://github.com/quillcraftsman/replay-wizard/releases
Project-URL: Download, https://pypi.org/project/replay-wizard/
Keywords: python,home-automation,automation,artificial-intelligence,replayer,capturing
Classifier: Development Status :: 5 - Production/Stable
Classifier: Intended Audience :: End Users/Desktop
Classifier: License :: OSI Approved :: MIT License
Classifier: Programming Language :: Python :: 3
Classifier: Environment :: Console
Classifier: Operating System :: OS Independent
Classifier: Topic :: Adaptive Technologies
Classifier: Topic :: Home Automation
Classifier: Topic :: Scientific/Engineering :: Artificial Intelligence
Requires-Python: >=3
License-File: LICENSE
Requires-Dist: pynput ==1.7.6
Requires-Dist: pydantic ==2.6.3
